[
  {
    "title": "#1",
    "items": [
      {
        "name": "Reik - Yo Quisiera (Video)",
        "url": "https://www.youtube.com/watch?v=QZKrLIoMyxY",
        "thumbnail": "https://i.ytimg.com/vi/QZKrLIoMyxY/hqdefault.jpg",
        "type": "youtubeVideo",
        "lang": "es",
        "created_at": 1691855673213,
        "category": {
          "id": "1",
          "name": "General"
        }
      },
      {
        "name": "La Ciencia Que Cambiará Tu Futuro | Dr. Bruce Lipton",
        "url": "https://www.youtube.com/watch?v=Bu54EO9nm_M",
        "thumbnail": "https://i.ytimg.com/vi/Bu54EO9nm_M/hqdefault.jpg",
        "type": "youtubeVideo",
        "lang": "es",
        "created_at": 1691855673213,
        "category": {
          "id": "1",
          "name": "General"
        }
      },
      {
        "name": "Luis Fonsi - Despacito ft. Daddy Yankee",
        "url": "https://www.youtube.com/watch?v=kJQP7kiw5Fk",
        "thumbnail": "https://i.ytimg.com/vi/kJQP7kiw5Fk/hqdefault.jpg",
        "type": "youtubeVideo",
        "lang": "es",
        "created_at": 1691855673213,
        "category": {
          "id": "1",
          "name": "General"
        }
      },
      {
        "name": "Daddy Yankee & Snow - Con Calma (Video Oficial)",
        "url": "https://www.youtube.com/watch?v=DiItGE3eAyQ",
        "thumbnail": "https://i.ytimg.com/vi/DiItGE3eAyQ/hqdefault.jpg",
        "type": "youtubeVideo",
        "lang": "es",
        "created_at": 1691855673213,
        "category": {
          "id": "1",
          "name": "General"
        }
      },
      {
        "name": "Carlos Vives - El Orgullo de Mi Patria (Official Video)",
        "url": "https://www.youtube.com/watch?v=Yq79ibIx2sc",
        "thumbnail": "https://i.ytimg.com/vi/Yq79ibIx2sc/hqdefault.jpg",
        "type": "youtubeVideo",
        "lang": "es",
        "created_at": 1691855673213,
        "category": {
          "id": "1",
          "name": "General"
        }
      },
      {
        "type": "message"
      }
    ]
  },
  {
    "title": "#2",
    "items": [
      {
        "name": "Sebastián Yatra - No Hay Nadie Más (Official Video)",
        "url": "https://www.youtube.com/watch?v=sD9_l3oDOag",
        "thumbnail": "https://i.ytimg.com/vi/sD9_l3oDOag/hqdefault.jpg",
        "type": "youtubeVideo",
        "lang": "es",
        "created_at": 1691856994217,
        "category": {
          "id": "1",
          "name": "General"
        }
      },
      {
        "name": "Sebastián Yatra, Reik - Un Año (Official Video)",
        "url": "https://www.youtube.com/watch?v=ghAvJMxE1qo",
        "thumbnail": "https://i.ytimg.com/vi/ghAvJMxE1qo/hqdefault.jpg",
        "type": "youtubeVideo",
        "lang": "es",
        "created_at": 1691856994217,
        "category": {
          "id": "1",
          "name": "General"
        }
      },
      {
        "name": "Cómo surgió el temido Imperio mongol de Gengis Kan y qué causó su desintegración",
        "url": "https://www.youtube.com/watch?v=_gpwkxgRc6A",
        "thumbnail": "https://i.ytimg.com/vi/_gpwkxgRc6A/hqdefault.jpg",
        "type": "youtubeVideo",
        "lang": "es",
        "created_at": 1691856994217,
        "category": {
          "id": "1",
          "name": "General"
        }
      },
      {
        "name": "El Mayor Secreto Del Autocontrol (Úsalo Todos Los Días)",
        "url": "https://www.youtube.com/watch?v=-MMLCvRznHk&t=26s",
        "thumbnail": "https://i.ytimg.com/vi/-MMLCvRznHk/hqdefault.jpg",
        "type": "youtubeVideo",
        "lang": "es",
        "created_at": 1691856994217,
        "category": {
          "id": "1",
          "name": "General"
        }
      },
      {
        "name": "Esto es lo que El Niño le hará a la Tierra en 2024",
        "url": "https://www.youtube.com/watch?v=IEbMfuwpWsI",
        "thumbnail": "https://i.ytimg.com/vi/IEbMfuwpWsI/hqdefault.jpg",
        "type": "youtubeVideo",
        "lang": "es",
        "created_at": 1691856994217,
        "category": {
          "id": "1",
          "name": "General"
        }
      },
      {
        "type": "message"
      }
    ]
  },
  {
    "title": "#3",
    "items": [
      {
        "name": "Daddy Yankee & Snow - Con Calma (Video Oficial)",
        "url": "https://www.youtube.com/watch?v=DiItGE3eAyQ",
        "thumbnail": "https://i.ytimg.com/vi/DiItGE3eAyQ/hqdefault.jpg",
        "type": "youtubeVideo",
        "lang": "es",
        "created_at": 1691855673213,
        "category": {
          "id": "1",
          "name": "General"
        }
      },
      {
        "name": "Carlos Vives - El Orgullo de Mi Patria (Official Video)",
        "url": "https://www.youtube.com/watch?v=Yq79ibIx2sc",
        "thumbnail": "https://i.ytimg.com/vi/Yq79ibIx2sc/hqdefault.jpg",
        "type": "youtubeVideo",
        "lang": "es",
        "created_at": 1691855673213,
        "category": {
          "id": "1",
          "name": "General"
        }
      },
      {
        "name": "Reik - Yo Quisiera (Video)",
        "url": "https://www.youtube.com/watch?v=QZKrLIoMyxY",
        "thumbnail": "https://i.ytimg.com/vi/QZKrLIoMyxY/hqdefault.jpg",
        "type": "youtubeVideo",
        "lang": "es",
        "created_at": 1691855673213,
        "category": {
          "id": "1",
          "name": "General"
        }
      },
      {
        "name": "La Ciencia Que Cambiará Tu Futuro | Dr. Bruce Lipton",
        "url": "https://www.youtube.com/watch?v=Bu54EO9nm_M",
        "thumbnail": "https://i.ytimg.com/vi/Bu54EO9nm_M/hqdefault.jpg",
        "type": "youtubeVideo",
        "lang": "es",
        "created_at": 1691855673213,
        "category": {
          "id": "1",
          "name": "General"
        }
      },
      {
        "name": "Luis Fonsi - Despacito ft. Daddy Yankee",
        "url": "https://www.youtube.com/watch?v=kJQP7kiw5Fk",
        "thumbnail": "https://i.ytimg.com/vi/kJQP7kiw5Fk/hqdefault.jpg",
        "type": "youtubeVideo",
        "lang": "es",
        "created_at": 1691855673213,
        "category": {
          "id": "1",
          "name": "General"
        }
      },
      {
        "type": "message"
      }
    ]
  },
  {
    "title": "#4",
    "items": [
      {
        "name": "Cómo surgió el temido Imperio mongol de Gengis Kan y qué causó su desintegración",
        "url": "https://www.youtube.com/watch?v=_gpwkxgRc6A",
        "thumbnail": "https://i.ytimg.com/vi/_gpwkxgRc6A/hqdefault.jpg",
        "type": "youtubeVideo",
        "lang": "es",
        "created_at": 1691856994217,
        "category": {
          "id": "1",
          "name": "General"
        }
      },
      {
        "name": "El Mayor Secreto Del Autocontrol (Úsalo Todos Los Días)",
        "url": "https://www.youtube.com/watch?v=-MMLCvRznHk&t=26s",
        "thumbnail": "https://i.ytimg.com/vi/-MMLCvRznHk/hqdefault.jpg",
        "type": "youtubeVideo",
        "lang": "es",
        "created_at": 1691856994217,
        "category": {
          "id": "1",
          "name": "General"
        }
      },
      {
        "name": "Esto es lo que El Niño le hará a la Tierra en 2024",
        "url": "https://www.youtube.com/watch?v=IEbMfuwpWsI",
        "thumbnail": "https://i.ytimg.com/vi/IEbMfuwpWsI/hqdefault.jpg",
        "type": "youtubeVideo",
        "lang": "es",
        "created_at": 1691856994217,
        "category": {
          "id": "1",
          "name": "General"
        }
      },
      {
        "name": "Sebastián Yatra - No Hay Nadie Más (Official Video)",
        "url": "https://www.youtube.com/watch?v=sD9_l3oDOag",
        "thumbnail": "https://i.ytimg.com/vi/sD9_l3oDOag/hqdefault.jpg",
        "type": "youtubeVideo",
        "lang": "es",
        "created_at": 1691856994217,
        "category": {
          "id": "1",
          "name": "General"
        }
      },
      {
        "name": "Sebastián Yatra, Reik - Un Año (Official Video)",
        "url": "https://www.youtube.com/watch?v=ghAvJMxE1qo",
        "thumbnail": "https://i.ytimg.com/vi/ghAvJMxE1qo/hqdefault.jpg",
        "type": "youtubeVideo",
        "lang": "es",
        "created_at": 1691856994217,
        "category": {
          "id": "1",
          "name": "General"
        }
      },
      {
        "type": "message"
      }
    ]
  }
]